nginx_conf_tool/__init__.py
nginx_conf_tool/parser.py
nginx_conf_tool/tree.py
nginx_conf_tool-1.1.0.dist-info/METADATA
nginx_conf_tool-1.1.0.dist-info/WHEEL
nginx_conf_tool-1.1.0.dist-info/entry_points.txt
nginx_conf_tool-1.1.0.dist-info/licenses/LICENSE
nginx_conf_tool-1.1.0.dist-info/RECORD
