Metadata-Version: 2.4
Name: nginx-conf-tool
Version: 1.1.0
Summary: Add your description here
Author-email: Hai Vu <haivu2004@gmail.com>
License-File: LICENSE
Requires-Python: >=3.13
Requires-Dist: click>=8.1.8
Requires-Dist: crossplane>=0.5.8
